django_cattrs_fields/__init__.py
django_cattrs_fields/converters/__init__.py
django_cattrs_fields/converters/bson.py
django_cattrs_fields/converters/cbor2.py
django_cattrs_fields/converters/json.py
django_cattrs_fields/converters/msgpack.py
django_cattrs_fields/converters/msgspec.py
django_cattrs_fields/converters/orjson.py
django_cattrs_fields/converters/pyyaml.py
django_cattrs_fields/converters/register_hooks.py
django_cattrs_fields/converters/tomlkit.py
django_cattrs_fields/converters/ujson.py
django_cattrs_fields/fields/__init__.py
django_cattrs_fields/fields/files.py
django_cattrs_fields/hooks/__init__.py
django_cattrs_fields/hooks/bool_hooks.py
django_cattrs_fields/hooks/char_hooks.py
django_cattrs_fields/hooks/date_hooks.py
django_cattrs_fields/hooks/empty_hooks.py
django_cattrs_fields/hooks/file_hooks.py
django_cattrs_fields/hooks/number_hooks.py
django_cattrs_fields/utils/decimal.py
django_cattrs_fields/utils/timezone.py
django_cattrs_fields/validators/__init__.py
django_cattrs_fields-0.0.1.dist-info/METADATA
django_cattrs_fields-0.0.1.dist-info/WHEEL
django_cattrs_fields-0.0.1.dist-info/licenses/LICENSE
django_cattrs_fields-0.0.1.dist-info/RECORD
