Metadata-Version: 2.4
Name: django-cattrs-fields
Version: 0.0.1
Summary: django data type support for cattrs
Author-email: amirreza <amir.rsf1380@gmail.com>
License-Expression: BSD-3-Clause
License-File: LICENSE
Classifier: Development Status :: 1 - Planning
Classifier: Environment :: Web Environment
Classifier: Framework :: Django
Classifier: Framework :: Django :: 5.2
Classifier: Framework :: Django :: 6.0
Classifier: Intended Audience :: Developers
Classifier: Operating System :: OS Independent
Classifier: Programming Language :: Python
Classifier: Programming Language :: Python :: 3
Classifier: Programming Language :: Python :: 3 :: Only
Classifier: Programming Language :: Python :: 3.12
Classifier: Programming Language :: Python :: 3.13
Classifier: Programming Language :: Python :: 3.14
Classifier: Topic :: Internet :: WWW/HTTP
Classifier: Topic :: Software Development :: Libraries
Requires-Python: >=3.12
Requires-Dist: cattrs>=25.3.0
Requires-Dist: django>=6.0
Provides-Extra: bson
Requires-Dist: pymongo>=4.4.0; extra == 'bson'
Provides-Extra: cbor2
Requires-Dist: cbor2>=5.4.6; extra == 'cbor2'
Provides-Extra: msgpack
Requires-Dist: msgpack>=1.0.5; extra == 'msgpack'
Provides-Extra: msgspec
Requires-Dist: msgspec>=0.19.0; (implementation_name == 'cpython') and extra == 'msgspec'
Provides-Extra: orjson
Requires-Dist: orjson>=3.11.3; (implementation_name == 'cpython') and extra == 'orjson'
Provides-Extra: pyyaml
Requires-Dist: pyyaml>=6.0; extra == 'pyyaml'
Provides-Extra: tomlkit
Requires-Dist: tomlkit>=0.11.8; extra == 'tomlkit'
Provides-Extra: ujson
Requires-Dist: ujson>=5.10.0; extra == 'ujson'
